README.md
setup.cfg
setup.py
distributions/Binomialdistribution.py
distributions/Gaussiandistribution.py
distributions/Generaldistribution.py
distributions/__init__.py
mg_prob_dist.egg-info/PKG-INFO
mg_prob_dist.egg-info/SOURCES.txt
mg_prob_dist.egg-info/dependency_links.txt
mg_prob_dist.egg-info/not-zip-safe
mg_prob_dist.egg-info/top_level.txt